TrakteerApiWrapper/__init__.py
TrakteerApiWrapper/main.py
trakteerapiwrapper-0.3.dist-info/licenses/LICENSE
trakteerapiwrapper-0.3.dist-info/METADATA
trakteerapiwrapper-0.3.dist-info/WHEEL
trakteerapiwrapper-0.3.dist-info/top_level.txt
trakteerapiwrapper-0.3.dist-info/RECORD
