Metadata-Version: 2.4
Name: TrakteerApiWrapper
Version: 0.3
Summary: A simple wrapper for the Trakteer API
Home-page: https://github.com/IndraBagus0/TrakteerApiWrapper
Author: Indra Bagus
Author-email: indrabusiness00@gmail.com
License: MIT
Keywords: trakteer,api,wrapper,python
Classifier: Development Status :: 4 - Beta
Classifier: Intended Audience :: Developers
Classifier: License :: OSI Approved :: MIT License
Classifier: Programming Language :: Python :: 3
Classifier: Programming Language :: Python :: 3.9
Classifier: Programming Language :: Python :: 3.10
Classifier: Programming Language :: Python :: 3.11
Classifier: Programming Language :: Python :: 3.12
License-File: LICENSE
Requires-Dist: requests
Dynamic: author
Dynamic: author-email
Dynamic: classifier
Dynamic: description
Dynamic: description-content-type
Dynamic: home-page
Dynamic: keywords
Dynamic: license
Dynamic: license-file
Dynamic: requires-dist
Dynamic: summary
